alibabacloud_adb20211201/__init__.py
alibabacloud_adb20211201/client.py
alibabacloud_adb20211201/models/__init__.py
alibabacloud_adb20211201/models/_adb_4mysql_spark_diagnosis_info.py
alibabacloud_adb20211201/models/_allocate_cluster_public_connection_request.py
alibabacloud_adb20211201/models/_allocate_cluster_public_connection_response.py
alibabacloud_adb20211201/models/_allocate_cluster_public_connection_response_body.py
alibabacloud_adb20211201/models/_apply_advice_by_id_request.py
alibabacloud_adb20211201/models/_apply_advice_by_id_response.py
alibabacloud_adb20211201/models/_apply_advice_by_id_response_body.py
alibabacloud_adb20211201/models/_attach_user_enirequest.py
alibabacloud_adb20211201/models/_attach_user_eniresponse.py
alibabacloud_adb20211201/models/_attach_user_eniresponse_body.py
alibabacloud_adb20211201/models/_batch_apply_advice_by_id_list_request.py
alibabacloud_adb20211201/models/_batch_apply_advice_by_id_list_response.py
alibabacloud_adb20211201/models/_batch_apply_advice_by_id_list_response_body.py
alibabacloud_adb20211201/models/_bind_account_request.py
alibabacloud_adb20211201/models/_bind_account_response.py
alibabacloud_adb20211201/models/_bind_account_response_body.py
alibabacloud_adb20211201/models/_bind_dbresource_group_with_user_request.py
alibabacloud_adb20211201/models/_bind_dbresource_group_with_user_response.py
alibabacloud_adb20211201/models/_bind_dbresource_group_with_user_response_body.py
alibabacloud_adb20211201/models/_cancel_spark_repl_statement_request.py
alibabacloud_adb20211201/models/_cancel_spark_repl_statement_response.py
alibabacloud_adb20211201/models/_cancel_spark_repl_statement_response_body.py
alibabacloud_adb20211201/models/_cancel_spark_warehouse_batch_sqlrequest.py
alibabacloud_adb20211201/models/_cancel_spark_warehouse_batch_sqlresponse.py
alibabacloud_adb20211201/models/_cancel_spark_warehouse_batch_sqlresponse_body.py
alibabacloud_adb20211201/models/_check_bind_ram_user_request.py
alibabacloud_adb20211201-3.7.1.dist-info/LICENSE
alibabacloud_adb20211201-3.7.1.dist-info/METADATA
alibabacloud_adb20211201-3.7.1.dist-info/WHEEL
alibabacloud_adb20211201-3.7.1.dist-info/top_level.txt
alibabacloud_adb20211201-3.7.1.dist-info/RECORD
